benchmarks/__init__.py
examples/__init__.py
mithril/__init__.py
mithril/core.py
mithril/backends/__init__.py
mithril/backends/backend.py
mithril/backends/parallel.py
mithril/backends/utils.py
mithril/backends/with_autograd/__init__.py
mithril/backends/with_autograd/common_primitives.py
mithril/backends/with_autograd/jax_backend/__init__.py
mithril/backends/with_autograd/jax_backend/backend.py
mithril/backends/with_autograd/jax_backend/ops.py
mithril/backends/with_autograd/jax_backend/parallel.py
mithril/backends/with_autograd/jax_backend/utils.py
mithril/backends/with_autograd/mlx_backend/__init__.py
mithril/backends/with_autograd/mlx_backend/backend.py
mithril/backends/with_autograd/mlx_backend/ops.py
mithril/backends/with_autograd/mlx_backend/utils.py
mithril/backends/with_autograd/torch_backend/__init__.py
mithril/backends/with_autograd/torch_backend/backend.py
mithril/backends/with_autograd/torch_backend/ops.py
mithril/backends/with_autograd/torch_backend/parallel.py
mithril/backends/with_autograd/torch_backend/stensor.py
mithril/backends/with_autograd/torch_backend/utils.py
mithril/backends/with_manualgrad/__init__.py
mithril/backends/with_manualgrad/common_primitives.py
mithril/backends/with_manualgrad/c_backend/__init__.py
mithril/backends/with_manualgrad/c_backend/backend.py
mithril/backends/with_manualgrad/c_backend/src/array.c
mithril/backends/with_manualgrad/c_backend/src/array.h
mithril/backends/with_manualgrad/c_backend/src/array.py
mithril/backends/with_manualgrad/c_backend/src/array.pyi
mithril/backends/with_manualgrad/c_backend/src/cbackend.h
mithril/backends/with_manualgrad/c_backend/src/compile.sh
mithril/backends/with_manualgrad/c_backend/src/libmithrilc.so
mithril/backends/with_manualgrad/c_backend/src/main.c
mithril/backends/with_manualgrad/c_backend/src/ops.c
mithril/backends/with_manualgrad/c_backend/src/ops.h
mithril/backends/with_manualgrad/c_backend/src/utils.h
mithril/backends/with_manualgrad/c_backend/src/utils.py
sarmal-0.3.0.dist-info/LICENSE
sarmal-0.3.0.dist-info/METADATA
sarmal-0.3.0.dist-info/NOTICE
sarmal-0.3.0.dist-info/WHEEL
sarmal-0.3.0.dist-info/top_level.txt
sarmal-0.3.0.dist-info/RECORD
